wikimedia_cli/__init__.py
wikimedia_cli/__main__.py
wikimedia_cli/cli.py
wikimedia_cli/commands/__init__.py
wikimedia_cli/commands/util.py
wikimedia_cli/commands/wikipedia/article.py
wikimedia_cli/commands/wikipedia/http.py
wikimedia_cli/commands/wikipedia/revision.py
wikimedia_cli/commands/wikipedia/search.py
wikimedia_cli/commands/wiktionary/http.py
wikimedia_cli/commands/wiktionary/phrase.py
wikimedia_cli/commands/wiktionary/revision.py
wikimedia_cli/commands/wiktionary/search.py
wikimedia_cli-0.1.0.dist-info/entry_points.txt
wikimedia_cli-0.1.0.dist-info/LICENSE
wikimedia_cli-0.1.0.dist-info/WHEEL
wikimedia_cli-0.1.0.dist-info/METADATA
wikimedia_cli-0.1.0.dist-info/RECORD
