Metadata-Version: 2.1
Name: wikimedia-cli
Version: 0.1.0
Summary: Minimally dependent CLI for Wikimedia projects
Home-page: https://github.com/g3ner1c/wikimedia-cli
License: MIT
Keywords: wikimedia,wikipedia,wiktionary,cli
Author: Sky "g3ner1c" H.
Author-email: g3ner1c-sky@pm.me
Requires-Python: >=3.7,<4.0
Classifier: Environment :: Console
Classifier: License :: OSI Approved :: MIT License
Classifier: Programming Language :: Python :: 3
Classifier: Programming Language :: Python :: 3.10
Classifier: Programming Language :: Python :: 3.7
Classifier: Programming Language :: Python :: 3.8
Classifier: Programming Language :: Python :: 3.9
Classifier: Topic :: Utilities
Provides-Extra: docs
Provides-Extra: lint
Requires-Dist: Sphinx (>=4.4); extra == "docs"
Requires-Dist: furo (>=2022); extra == "docs"
Requires-Dist: myst-parser (>=0.17.0); extra == "docs"
Requires-Dist: requests (>=2.27,<3.0)
Project-URL: Documentation, https://wikimedia-cli.readthedocs.io/en/latest/
Project-URL: Repository, https://github.com/g3ner1c/wikimedia-cli
